nonebot_plugin_skland_arksign-0.8.1.dist-info/METADATA
nonebot_plugin_skland_arksign-0.8.1.dist-info/WHEEL
nonebot_plugin_skland_arksign-0.8.1.dist-info/entry_points.txt
nonebot_plugin_skland_arksign-0.8.1.dist-info/licenses/LICENSE
nonebot_plugin_skland_arksign/__init__.py
nonebot_plugin_skland_arksign/alc_parser.py
nonebot_plugin_skland_arksign/command.py
nonebot_plugin_skland_arksign/config.py
nonebot_plugin_skland_arksign/constants.py
nonebot_plugin_skland_arksign/depends.py
nonebot_plugin_skland_arksign/did/__init__.py
nonebot_plugin_skland_arksign/did/api.py
nonebot_plugin_skland_arksign/did/html_simulate/__init__.py
nonebot_plugin_skland_arksign/did/html_simulate/static/fp.min.js
nonebot_plugin_skland_arksign/did/html_simulate/static/index.html
nonebot_plugin_skland_arksign/did/local_simulate.py
nonebot_plugin_skland_arksign/migrations/486a6e0eed5b_migrate_data.py
nonebot_plugin_skland_arksign/migrations/4bc53bd04337_init_db.py
nonebot_plugin_skland_arksign/migrations/__init__.py
nonebot_plugin_skland_arksign/model.py
nonebot_plugin_skland_arksign/sched.py
nonebot_plugin_skland_arksign/signin.py
nonebot_plugin_skland_arksign/utils.py
nonebot_plugin_skland_arksign-0.8.1.dist-info/RECORD
