Metadata-Version: 2.1
Name: nonebot-plugin-skland-arksign
Version: 0.8.1
Summary: 用于每日定时签到森空岛明日方舟的Nonebot插件
Author-Email: GuGuMur <222153315@qq.com>, Azide <rukuy@qq.com>
License: MIT
Classifier: Programming Language :: Python :: 3.10
Classifier: Programming Language :: Python :: 3.11
Classifier: Programming Language :: Python :: 3.12
Requires-Python: >=3.10
Requires-Dist: nonebot2>=2.2.1
Requires-Dist: httpx>=0.27.2
Requires-Dist: pydantic>=2.0.0
Requires-Dist: nonebot-plugin-apscheduler>=0.5.0
Requires-Dist: nonebot-plugin-alconna>=0.52.3
Requires-Dist: nonebot-plugin-datastore>=1.3.0
Requires-Dist: nonebot-plugin-session>=0.3.2
Requires-Dist: nonebot-plugin-session-saa>=0.2.0
Requires-Dist: nonebot-plugin-send-anything-anywhere>=0.6.1
Requires-Dist: nonebot-plugin-orm[default]>=0.7.6
Provides-Extra: sm-local
Requires-Dist: cryptography>=43.0.1; extra == "sm-local"
Provides-Extra: sm-htmlrender
Requires-Dist: nonebot-plugin-htmlrender>=0.3.5; extra == "sm-htmlrender"
